browserprofilecreator/BrowserProfileCreator.py
browserprofilecreator/Helper.py
browserprofilecreator/__init__.py
browserprofilecreator/cli.py
browserprofilecreator/click_placeholder.py
browserprofilecreator-0.1.1.dist-info/WHEEL
browserprofilecreator-0.1.1.dist-info/entry_points.txt
browserprofilecreator-0.1.1.dist-info/METADATA
browserprofilecreator-0.1.1.dist-info/RECORD
