Metadata-Version: 2.3
Name: browserprofilecreator
Version: 0.1.1
Summary: Folder-based isolated browser profile generator.
Requires-Python: >=3.12
